<annotation>
	<folder>a_semibreves_pieciolinia</folder>
	<filename>image_166.jpg</filename>
	<path>C:\Projects\a_semibreves_pieciolinia\image_166.jpg</path>
	<source>
		<database>Unknown</database>
	</source>
	<size>
		<width>4032</width>
		<height>3024</height>
		<depth>3</depth>
	</size>
	<segmented>0</segmented>
	<object>
		<name>semibreve_h</name>
		<pose>Unspecified</pose>
		<truncated>0</truncated>
		<difficult>0</difficult>
		<bndbox>
			<xmin>645</xmin>
			<ymin>313</ymin>
			<xmax>779</xmax>
			<ymax>635</ymax>
		</bndbox>
	</object>
	<object>
		<name>semibreve_c</name>
		<pose>Unspecified</pose>
		<truncated>0</truncated>
		<difficult>0</difficult>
		<bndbox>
			<xmin>1960</xmin>
			<ymin>353</ymin>
			<xmax>2092</xmax>
			<ymax>678</ymax>
		</bndbox>
	</object>
	<object>
		<name>semibreve_d</name>
		<pose>Unspecified</pose>
		<truncated>0</truncated>
		<difficult>0</difficult>
		<bndbox>
			<xmin>3176</xmin>
			<ymin>425</ymin>
			<xmax>3295</xmax>
			<ymax>775</ymax>
		</bndbox>
	</object>
	<object>
		<name>semibreve_a</name>
		<pose>Unspecified</pose>
		<truncated>0</truncated>
		<difficult>0</difficult>
		<bndbox>
			<xmin>457</xmin>
			<ymin>1222</ymin>
			<xmax>607</xmax>
			<ymax>1594</ymax>
		</bndbox>
	</object>
	<object>
		<name>semibreve_f</name>
		<pose>Unspecified</pose>
		<truncated>0</truncated>
		<difficult>0</difficult>
		<bndbox>
			<xmin>1892</xmin>
			<ymin>1247</ymin>
			<xmax>2017</xmax>
			<ymax>1581</ymax>
		</bndbox>
	</object>
	<object>
		<name>semibreve_c</name>
		<pose>Unspecified</pose>
		<truncated>0</truncated>
		<difficult>0</difficult>
		<bndbox>
			<xmin>3157</xmin>
			<ymin>1235</ymin>
			<xmax>3264</xmax>
			<ymax>1563</ymax>
		</bndbox>
	</object>
	<object>
		<name>semibreve_h</name>
		<pose>Unspecified</pose>
		<truncated>0</truncated>
		<difficult>0</difficult>
		<bndbox>
			<xmin>448</xmin>
			<ymin>2235</ymin>
			<xmax>595</xmax>
			<ymax>2588</ymax>
		</bndbox>
	</object>
	<object>
		<name>semibreve_f</name>
		<pose>Unspecified</pose>
		<truncated>0</truncated>
		<difficult>0</difficult>
		<bndbox>
			<xmin>1907</xmin>
			<ymin>2147</ymin>
			<xmax>2035</xmax>
			<ymax>2513</ymax>
		</bndbox>
	</object>
	<object>
		<name>semibreve_f</name>
		<pose>Unspecified</pose>
		<truncated>0</truncated>
		<difficult>0</difficult>
		<bndbox>
			<xmin>3220</xmin>
			<ymin>2122</ymin>
			<xmax>3326</xmax>
			<ymax>2478</ymax>
		</bndbox>
	</object>
</annotation>
